.travis.yml
CHANGES.txt
MANIFEST.in
README.txt
bootstrap.py
buildout.cfg
generate-sample-cert.sh
server.ini
setup.py
zope.conf
src/keas/__init__.py
src/keas.kmi.egg-info/PKG-INFO
src/keas.kmi.egg-info/SOURCES.txt
src/keas.kmi.egg-info/dependency_links.txt
src/keas.kmi.egg-info/entry_points.txt
src/keas.kmi.egg-info/namespace_packages.txt
src/keas.kmi.egg-info/not-zip-safe
src/keas.kmi.egg-info/requires.txt
src/keas.kmi.egg-info/top_level.txt
src/keas/kmi/README.txt
src/keas/kmi/__init__.py
src/keas/kmi/_compat.py
src/keas/kmi/configure.zcml
src/keas/kmi/facility.py
src/keas/kmi/facility.txt
src/keas/kmi/interfaces.py
src/keas/kmi/keyholder.py
src/keas/kmi/keyholder.txt
src/keas/kmi/persistent.py
src/keas/kmi/persistent.txt
src/keas/kmi/rest.py
src/keas/kmi/rest.zcml
src/keas/kmi/testclient.py
src/keas/kmi/testing.py
src/keas/kmi/tests.py
src/keas/kmi/wsgi.py